hooks/__init__.py
hooks/post_gen_project.py
hooks/pre_gen_project.py
cookiecutter_python_package-0.1.1.dist-info/LICENSE.rst
cookiecutter_python_package-0.1.1.dist-info/METADATA
cookiecutter_python_package-0.1.1.dist-info/WHEEL
cookiecutter_python_package-0.1.1.dist-info/top_level.txt
cookiecutter_python_package-0.1.1.dist-info/RECORD
